Workbook

Sheet RECEITA
A1: DESCRIÇÃO DA RECEITA(VALOR A RECEBER) | B1: AGOSTO/2026 | C1: SETEMBRO/2026 | D1: OUTUBRO/2026 | E1: NOVEMBRO/2026 | F1: DEZEMBRO/2026
A2: PAGAMENTO | B2: 3500 | C2: 3500 | D2: 3500 | E2: 3500 | F2: 3500
A3: FREELANCER | B3: 1200 | C3: 1200 | D3: 1200 | E3: 1200 | F3: 1200
A4: TOTAL | B4: =SUM(B2+B3) -> 4700 | C4: =SUM(C2+C3) -> 4700 | D4: =SUM(D2+D3) -> 4700 | E4: =SUM(E2+E3) -> 4700 | F4: =SUM(F2+F3) -> 4700

Sheet DESPESA
A1: DESCRICAO DA DESPESA(VALOR A PAGAR) | B1: 46235 | C1: SETEMBRO/2026 | D1: OUTUBRO/2026 | E1: NOVEMBRO/2026 | F1: DEZEMBRO/2026
A2: Aluguel/Moradia | B2: 1800 | C2: 1800 | D2: 1800 | E2: 1800 | F2: 1800
A3: Alimentacao | B3: 1200 | C3: 1200 | D3: 1200 | E3: 1200 | F3: 1200
A4: Educação | B4: 300 | C4: 300 | D4: 300 | E4: 300 | F4: 300
A5: Lazer | B5: 300 | C5: 300 | D5: 300 | E5: 1500 | F5: 300
A6: Saúde | B6: 300 | C6: 300 | D6: 300 | E6: 300 | F6: 300
A7: Investimentos | B7: 0 | C7: 0 | D7: 0 | E7: 0 | F7: 0
A8: SALDO->SOMA DAS DESDPESAS | B8: =SUM(B2:B7) -> 3900 | C8: =SUM(C2:C7) -> 3900 | D8: =SUM(D2:D7) -> 3900 | E8: =SUM(E2:E7) -> 5100 | F8: =SUM(F2:F7) -> 3900

Sheet SALDO-MENSAL
A1: DESCRICAO | B1: 46235 | C1: SETEMBRO/2026 | D1: OUTUBRO/2026 | E1: NOVEMBRO/2026 | F1: DEZEMBRO/2026
A2: RECEITAS | B2: =RECEITA!B4 -> 4700 | C2: =RECEITA!C4 -> 4700 | D2: =RECEITA!D4 -> 4700 | E2: =RECEITA!E4 -> 4700 | F2: =RECEITA!F4 -> 4700 | G2: =RECEITA!G4
A3: DESPESAS | B3: =DESPESA!B8 -> 3900 | C3: =DESPESA!C8 -> 3900 | D3: =DESPESA!D8 -> 3900 | E3: =DESPESA!E8 -> 5100 | F3: =DESPESA!F8 -> 3900 | G3: =DESPESA!G8
A4: SALDO MENSAL | B4: =B2-B3 -> 800 | C4: =C2-C3 -> 800 | D4: =D2-D3 -> 800 | E4: =E2-E3 -> -400 | F4: =F2-F3 -> 800
A5: FORMTACAO CONDICIONAL USANDO "SE" | B5: =IF(B4 < 0,"ALERTA!!", "TUDO OK") -> TUDO OK | C5: =IF(C4 < 0,"ALERTA!!", "TUDO OK") -> TUDO OK | D5: =IF(D4 < 0,"ALERTA!!", "TUDO OK") -> TUDO OK | E5: =IF(E4 < 0,"ALERTA!!", "TUDO OK") -> ALERTA!! | F5: =IF(F4 < 0,"ALERTA!!", "TUDO OK") -> TUDO OK

Sheet EXEMPLO-FILTROS-CLASSIFICACAO
A1: DESCRICAO DA DESPESA(VALOR A PAGAR) | B1: STATUS | C1: 46235 | D1: SETEMBRO/2026 | E1: OUTUBRO/2026 | F1: NOVEMBRO/2026 | G1: DEZEMBRO/2026
A2: Aluguel/Moradia | B2: CONFERIDO | C2: 1800 | D2: 1800 | E2: 1800 | F2: 1800 | G2: 1800
A3: Alimentacao | B3: CONFERIR | C3: 1200 | D3: 1200 | E3: 1200 | F3: 1200 | G3: 1200
A4: Educação | B4: CONFERIR | C4: 300 | D4: 300 | E4: 300 | F4: 300 | G4: 300
A5: Lazer | C5: 300 | D5: 300 | E5: 300 | F5: 300 | G5: 300
A6: Saúde | C6: 300 | D6: 300 | E6: 300 | F6: 300 | G6: 300
A7: Investimentos | C7: 0 | D7: 0 | E7: 0 | F7: 0 | G7: 0
A8: SALDO->SOMA DAS DESDPESAS | C8: =SUM(C2:C7) -> 3900 | D8: =SUM(D2:D7) -> 3900 | E8: =SUM(E2:E7) -> 3900 | F8: =SUM(F2:F7) -> 3900 | G8: =SUM(G2:G7) -> 3900
